minerboard/__init__.py
minerboard/config/config.ini
minerboard/minerboard_core/__init__.py
minerboard/minerboard_core/minerboard_uploder.py
minerboard-0.0.13.dist-info/DESCRIPTION.rst
minerboard-0.0.13.dist-info/METADATA
minerboard-0.0.13.dist-info/RECORD
minerboard-0.0.13.dist-info/WHEEL
minerboard-0.0.13.dist-info/entry_points.txt
minerboard-0.0.13.dist-info/metadata.json
minerboard-0.0.13.dist-info/top_level.txt
